README.rst
setup.py
swifpy/__init__.py
swifpy/array.py
swifpy/dictionary.py
swifpy/optional.py
swifpy/types.py
swifpy.egg-info/PKG-INFO
swifpy.egg-info/SOURCES.txt
swifpy.egg-info/dependency_links.txt
swifpy.egg-info/requires.txt
swifpy.egg-info/top_level.txt