Metadata-Version: 1.1
Name: swifpy
Version: 0.0.1
Summary: Makes Python Swifty
Home-page: https://github.com/koher/swifpy
Author: koher
Author-email: koher@koherent.org
License: MIT
Keywords: swift swifty
Platform: UNKNOWN
Classifier: Development Status :: 3 - Alpha
Classifier: Intended Audience :: Developers
Classifier: Topic :: Utilities
Classifier: License :: OSI Approved :: MIT License
Classifier: Programming Language :: Python :: 3.6
